django_notification/__init__.py
django_notification/admin/__init__.py
django_notification/admin/deleted_notification.py
django_notification/admin/notification.py
django_notification/api/__init__.py
django_notification/api/filters/__init__.py
django_notification/api/filters/notification_filter.py
django_notification/api/paginations/__init__.py
django_notification/api/paginations/limit_offset_pagination.py
django_notification/api/routers/__init__.py
django_notification/api/routers/notification.py
django_notification/api/serializers/__init__.py
django_notification/api/serializers/group.py
django_notification/api/serializers/helper/__init__.py
django_notification/api/serializers/helper/get_serializer_cls.py
django_notification/api/serializers/notification.py
django_notification/api/serializers/simple_notification.py
django_notification/api/serializers/user.py
django_notification/api/throttlings/__init__.py
django_notification/api/throttlings/role_base_throttle.py
django_notification/api/views/__init__.py
django_notification/api/views/activity.py
django_notification/api/views/notification.py
django_notification/apps.py
django_notification/constants/__init__.py
django_notification/constants/default_settings.py
django_notification/constants/qs_types.py
django_notification/decorators/__init__.py
django_notification/decorators/action.py
django_notification/migrations/0001_initial.py
django_notification/migrations/0002_alter_deletednotification_deleted_at_and_more.py
django_notification/migrations/__init__.py
django_notification/mixins/__init__.py
django_notification/mixins/admin_permission.py
django_notification/mixins/config_api_attrs.py
django_notification/mixins/disable_api_methods.py
django_notification/models/__init__.py
django_notification/models/deleted_notification.py
django_notification/models/helper/__init__.py
django_notification/models/helper/enums/status_choices.py
django_notification/models/notification.py
django_notification/models/notification_recipient.py
dj_notification_api-1.2.0.dist-info/AUTHORS.md
dj_notification_api-1.2.0.dist-info/LICENCE
dj_notification_api-1.2.0.dist-info/METADATA
dj_notification_api-1.2.0.dist-info/WHEEL
dj_notification_api-1.2.0.dist-info/RECORD
