Metadata-Version: 2.1
Name: dj-notification-api
Version: 1.2.0
Summary: A Django package developed by Lazarus for efficiently handling notifications through various APIs
License: MIT
Keywords: django_notification,django,notification,django-notification
Author: ARYAN-NIKNEZHAD
Author-email: aryan513966@gmail.com
Requires-Python: >=3.9,<4.0
Classifier: Development Status :: 3 - Alpha
Classifier: Environment :: Web Environment
Classifier: Framework :: Django
Classifier: Framework :: Django :: 4.2
Classifier: Framework :: Django :: 5.0
Classifier: Framework :: Django :: 5.1
Classifier: Intended Audience :: Developers
Classifier: License :: OSI Approved :: MIT License
Classifier: Operating System :: OS Independent
Classifier: Programming Language :: Python
Classifier: Programming Language :: Python :: 3
Classifier: Programming Language :: Python :: 3.9
Classifier: Programming Language :: Python :: 3.10
Classifier: Programming Language :: Python :: 3.11
Classifier: Programming Language :: Python :: 3.12
Classifier: Programming Language :: Python :: 3 :: Only
Classifier: Programming Language :: Python :: 3.13
Classifier: Topic :: Software Development :: Libraries :: Python Modules
Requires-Dist: django (>=4.2,<5.0) ; python_version >= "3.9" and python_version < "3.10"
Requires-Dist: django (>=4.2,<5.3) ; python_version >= "3.10"
Requires-Dist: django-filter (>=24.3,<25.0)
Requires-Dist: djangorestframework (>=3.14.0,<4.0.0)
Project-URL: Changelog, https://github.com/lazarus-org/dj-notification-api/blob/main/CHANGELOG.md
Project-URL: Documentation, https://django-notification.readthedocs.io
Project-URL: Issues, https://github.com/lazarus-org/dj-notification-api/issues
Project-URL: Source Code, https://github.com/Lazarus-org/dj-notification-api
